django_directed/__init__.py
django_directed/admin.py
django_directed/apps.py
django_directed/context_managers.py
django_directed/exceptions.py
django_directed/fields.py
django_directed/manager_methods.py
django_directed/model_methods.py
django_directed/models.py
django_directed/query_utils.py
django_directed/queryset_methods.py
django_directed/urls.py
django_directed/validators.py
django_directed/views.py
django_directed/models/__init__.py
django_directed/models/abstract_base_graph_models.py
django_directed/models/abstract_base_models.py
django_directed/models/abstract_graph_models.py
django_directed/models/model_factory.py
django_directed/static/css/django_directed.css
django_directed/static/js/django_directed.js
django_directed/templates/django_directed/base.html
django_directed/templatetags/__init__.py
django_directed/test_utils/__init__.py
django_directed/test_utils/test_app/__init__.py
django_directed/test_utils/test_app/admin.py
django_directed/test_utils/test_app/apps.py
django_directed/test_utils/test_app/models.py
django_directed/test_utils/test_app/migrations/__init__.py
django_directed-0.1.3.dist-info/AUTHORS.md
django_directed-0.1.3.dist-info/LICENSE
django_directed-0.1.3.dist-info/METADATA
django_directed-0.1.3.dist-info/WHEEL
django_directed-0.1.3.dist-info/top_level.txt
django_directed-0.1.3.dist-info/RECORD
