Metadata-Version: 2.1
Name: django-directed
Version: 0.1.3
Summary: Tools for building, querying, manipulating, and exporting directed graphs with django
Home-page: https://github.com/jacklinke/django-directed/
Author: Jack Linke
Author-email: jack@watervize.com
License: Apache Software License
Project-URL: Documentation, https://django-directed.readthedocs.io/en/latest/
Project-URL: Source, https://github.com/jacklinke/django-directed/
Project-URL: Tracker, https://github.com/jacklinke/django-directed/issues
Keywords: django-directed,graph,tree,dag,network,directed,acyclic,postgres,cte
Platform: UNKNOWN
Classifier: Development Status :: 3 - Alpha
Classifier: Intended Audience :: Developers
Classifier: License :: OSI Approved :: Apache Software License
Classifier: Programming Language :: Python
Classifier: Programming Language :: Python :: 3.7
Classifier: Programming Language :: Python :: 3.8
Classifier: Programming Language :: Python :: 3.9
Classifier: Programming Language :: Python :: 3.10
Classifier: Operating System :: OS Independent
Classifier: Topic :: Software Development :: Libraries
Classifier: Topic :: Database
Classifier: Topic :: Utilities
Classifier: Environment :: Web Environment
Classifier: Framework :: Django
Classifier: Framework :: Django :: 2.2
Classifier: Framework :: Django :: 3.0
Classifier: Framework :: Django :: 3.1
Classifier: Framework :: Django :: 3.2
Requires-Python: >=3.7, <4
Requires-Dist: django (>=2.2)
Provides-Extra: all
